prompt_templates/__init__.py
prompt_templates/constants.py
prompt_templates/populators.py
prompt_templates/prompt_templates.py
prompt_templates/utils.py
prompt_templates-0.0.16.dist-info/LICENSE.txt
prompt_templates-0.0.16.dist-info/METADATA
prompt_templates-0.0.16.dist-info/WHEEL
prompt_templates-0.0.16.dist-info/RECORD
