Metadata-Version: 2.3
Name: prompt-templates
Version: 0.0.16
Summary: A library for working with prompt templates locally or on the Hugging Face Hub.
License: Appache-2.0
Author: MoritzLaurer
Author-email: moritz@huggingface.co
Requires-Python: >=3.10,<4.0
Classifier: License :: Other/Proprietary License
Classifier: Programming Language :: Python :: 3
Classifier: Programming Language :: Python :: 3.10
Classifier: Programming Language :: Python :: 3.11
Classifier: Programming Language :: Python :: 3.12
Classifier: Programming Language :: Python :: 3.13
Provides-Extra: inference
Requires-Dist: accelerate (>=1.2.0,<2.0.0) ; extra == "inference"
Requires-Dist: anthropic (>=0.40.0,<0.41.0) ; extra == "inference"
Requires-Dist: backports-tarfile (>=1.2.0,<2.0.0) ; python_version < "3.12"
Requires-Dist: boto3 (>=1.35.78,<2.0.0) ; extra == "inference"
Requires-Dist: datasets (>=3.2.0,<4.0.0)
Requires-Dist: google-genai (>=0.4.0,<0.5.0) ; extra == "inference"
Requires-Dist: huggingface-hub (>=0.26.5,<0.27.0)
Requires-Dist: jinja2 (>=3.1.4,<4.0.0)
Requires-Dist: langchain-anthropic (>=0.2.3,<0.3.0) ; extra == "inference"
Requires-Dist: langchain-core (>=0.3.12,<0.4.0) ; extra == "inference"
Requires-Dist: langchain-openai (>=0.2.2,<0.3.0) ; extra == "inference"
Requires-Dist: langchainhub (>=0.1.21,<0.2.0) ; extra == "inference"
Requires-Dist: langgraph (>=0.2.38,<0.3.0) ; extra == "inference"
Requires-Dist: numpy (>=1.26.0,<2.0.0)
Requires-Dist: openai (>=1.57.2,<2.0.0) ; extra == "inference"
Requires-Dist: python-dotenv (>=1.0.1,<2.0.0)
Requires-Dist: ruamel-yaml (>=0.18.6,<0.19.0)
Requires-Dist: transformers (>=4.47.0,<5.0.0) ; extra == "inference"
Requires-Dist: yfinance (>=0.2.50,<0.3.0) ; extra == "inference"
Project-URL: Homepage, https://github.com/MoritzLaurer/prompt_templates
